PyAthenaJDBC_qubole-1.3.4.dist-info/METADATA
PyAthenaJDBC_qubole-1.3.4.dist-info/RECORD
PyAthenaJDBC_qubole-1.3.4.dist-info/WHEEL
PyAthenaJDBC_qubole-1.3.4.dist-info/entry_points.txt
PyAthenaJDBC_qubole-1.3.4.dist-info/top_level.txt
pyathenajdbc/QuboleJDBC41.jar
pyathenajdbc/__init__.py
pyathenajdbc/connection.py
pyathenajdbc/converter.py
pyathenajdbc/cursor.py
pyathenajdbc/error.py
pyathenajdbc/formatter.py
pyathenajdbc/sqlalchemy_athena.py
pyathenajdbc/util.py
tests/__init__.py
tests/conftest.py
tests/test_cursor.py
tests/test_formatter.py
tests/test_sqlalchemy_athena.py
tests/test_util.py
tests/util.py
