Metadata-Version: 2.1
Name: PyAthenaJDBC-qubole
Version: 1.3.4
Summary: Python DB API 2.0 (PEP 249) compliant wrapper for Amazon Athena JDBC driver
Home-page: https://github.com/tanaya1234/PyAthenaJDBC-1
Author: laughingman7743
Author-email: laughingman7743@gmail.com
License: MIT License
Platform: UNKNOWN
Classifier: Development Status :: 4 - Beta
Classifier: Intended Audience :: Developers
Classifier: License :: OSI Approved :: MIT License
Classifier: Operating System :: OS Independent
Classifier: Topic :: Database :: Front-Ends
Classifier: Programming Language :: Java
Classifier: Programming Language :: Python :: 2
Classifier: Programming Language :: Python :: 2.7
Classifier: Programming Language :: Python :: 3
Classifier: Programming Language :: Python :: 3.4
Classifier: Programming Language :: Python :: 3.5
Classifier: Programming Language :: Python :: 3.6
Provides-Extra: SQLAlchemy
Provides-Extra: Pandas
Requires-Dist: future
Requires-Dist: jpype1 (>=0.6.0)
Requires-Dist: botocore (>=1.0.0)
Provides-Extra: Pandas
Requires-Dist: pandas (>=0.19.0); extra == 'Pandas'
Provides-Extra: SQLAlchemy
Requires-Dist: SQLAlchemy (>=1.0.0); extra == 'SQLAlchemy'
